modoole_test/__about__.py
modoole_test/__init__.py
modoole_test/cli.py
modoole_test-0.0.1.dist-info/METADATA
modoole_test-0.0.1.dist-info/WHEEL
modoole_test-0.0.1.dist-info/entry_points.txt
modoole_test-0.0.1.dist-info/licenses/LICENSE.txt
modoole_test-0.0.1.dist-info/RECORD
