Metadata-Version: 2.3
Name: modoole-test
Version: 0.0.1
Project-URL: Documentation, https://github.com/Michael Dahl/modoole-test#readme
Project-URL: Issues, https://github.com/Michael Dahl/modoole-test/issues
Project-URL: Source, https://github.com/Michael Dahl/modoole-test
Author-email: Michael Dahl <michael@dahl.software>
License: MIT
Classifier: Development Status :: 4 - Beta
Classifier: Programming Language :: Python
Classifier: Programming Language :: Python :: 3.8
Classifier: Programming Language :: Python :: 3.9
Classifier: Programming Language :: Python :: 3.10
Classifier: Programming Language :: Python :: 3.11
Classifier: Programming Language :: Python :: 3.12
Classifier: Programming Language :: Python :: Implementation :: CPython
Classifier: Programming Language :: Python :: Implementation :: PyPy
Requires-Python: >=3.8
Requires-Dist: odoo
Requires-Dist: typer
Requires-Dist: watchdog
